README.md
setup.py
hzyUtils/__init__.py
hzyUtils/student.py
hzyUtils.egg-info/PKG-INFO
hzyUtils.egg-info/SOURCES.txt
hzyUtils.egg-info/dependency_links.txt
hzyUtils.egg-info/top_level.txt