Metadata-Version: 2.1
Name: hzyUtils
Version: 1.0.0
Summary: hzyUtils
Home-page: https://mmbiz.qpic.cn/mmbiz_jpg/g82uB8Bp44lVfsYGZJ2JlibDIqBJR6KxShuB2RTzNTVE0k9H7S3oc0FLfjLY69EWlElB3zX5EHqMxOaQibSwLGwA/0?wx_fmt=jpeg
Author: 大轰
Author-email: fondadam@hotmail.com
License: BSD License
Platform: all
Classifier: Intended Audience :: Developers
Classifier: Operating System :: OS Independent
Classifier: Natural Language :: Chinese (Simplified)
Classifier: Programming Language :: Python :: 3.7
Classifier: Programming Language :: Python :: 3.8
Classifier: Programming Language :: Python :: 3.9
Classifier: Topic :: Software Development :: Libraries
